afromessage/__init__.py
afromessage/afromessage_service.py
afromessage_service-0.1.0.dist-info/METADATA
afromessage_service-0.1.0.dist-info/WHEEL
afromessage_service-0.1.0.dist-info/top_level.txt
afromessage_service-0.1.0.dist-info/RECORD
