Metadata-Version: 2.1
Name: afromessage-service
Version: 0.1.0
Summary: A wrapper around afromessage SMS service
Home-page: https://github.com/p4ndish/afromessage_service
Author: p4ndish
Author-email: tesfayedagim5@gmail.com
Classifier: Development Status :: 3 - Alpha
Classifier: Intended Audience :: Developers
Classifier: License :: OSI Approved :: MIT License
Classifier: Programming Language :: Python :: 3
Classifier: Programming Language :: Python :: 3.6
Classifier: Programming Language :: Python :: 3.7
Classifier: Programming Language :: Python :: 3.8
Classifier: Programming Language :: Python :: 3.9
Requires-Python: >=3.6
Requires-Dist: httpx
Provides-Extra: dev
Requires-Dist: pytest >=6.0.0 ; extra == 'dev'
Requires-Dist: pytest-cov >=2.10.0 ; extra == 'dev'
Requires-Dist: flake8 >=3.8.0 ; extra == 'dev'
Requires-Dist: black >=20.8b1 ; extra == 'dev'
Requires-Dist: twine ; extra == 'dev'
